configcrunch/__init__.py
configcrunch/_main.cp314t-win_amd64.pyd
configcrunch/_main.pyi
configcrunch/_util.py
configcrunch/py.typed
configcrunch-2.1.1.dist-info/licenses/LICENSE
configcrunch-2.1.1.dist-info/METADATA
configcrunch-2.1.1.dist-info/WHEEL
configcrunch-2.1.1.dist-info/top_level.txt
configcrunch-2.1.1.dist-info/RECORD
