Metadata-Version: 2.4
Name: configcrunch
Version: 2.1.1
Summary: Configuration parser based on YAML-Files with support for variables, overlaying and hierarchies
Author-email: Marco Köpcke <hello@capypara.de>
License-Expression: MIT
Project-URL: Repository, https://github.com/theCapypara/configcrunch
Project-URL: Documentation, https://configcrunch.readthedocs.io
Classifier: Development Status :: 4 - Beta
Classifier: Programming Language :: Python
Classifier: Programming Language :: Rust
Classifier: Intended Audience :: Developers
Classifier: Programming Language :: Python :: 3.11
Classifier: Programming Language :: Python :: 3.12
Classifier: Programming Language :: Python :: 3.13
Classifier: Programming Language :: Python :: 3.14
Requires-Python: >=3.11
License-File: LICENSE
Requires-Dist: schema>=0.7
Dynamic: license-file
